edc_metadata_rules/__init__.py
edc_metadata_rules/apps.py
edc_metadata_rules/decorators.py
edc_metadata_rules/logic.py
edc_metadata_rules/metadata_rule_evaluator.py
edc_metadata_rules/models.py
edc_metadata_rules/predicate.py
edc_metadata_rules/predicate_collection.py
edc_metadata_rules/rule.py
edc_metadata_rules/rule_evaluator.py
edc_metadata_rules/rule_group.py
edc_metadata_rules/rule_group_meta_options.py
edc_metadata_rules/rule_group_metaclass.py
edc_metadata_rules/settings.py
edc_metadata_rules/site.py
edc_metadata_rules/urls.py
edc_metadata_rules/wsgi.py
edc_metadata_rules/crf/__init__.py
edc_metadata_rules/crf/crf_rule.py
edc_metadata_rules/crf/crf_rule_group.py
edc_metadata_rules/management/__init__.py
edc_metadata_rules/management/commands/__init__.py
edc_metadata_rules/management/commands/validate_entry_status.py
edc_metadata_rules/management/commands/validate_rule_groups.py
edc_metadata_rules/requisition/__init__.py
edc_metadata_rules/requisition/requisition_rule.py
edc_metadata_rules/requisition/requisition_rule_group.py
edc_metadata_rules/tests/__init__.py
edc_metadata_rules/tests/models.py
edc_metadata_rules/tests/reference_configs.py
edc_metadata_rules/tests/visit_schedule.py
edc_metadata_rules/tests/tests/__init__.py
edc_metadata_rules/tests/tests/test_crf_rule_group_gender.py
edc_metadata_rules/tests/tests/test_crf_rule_groups.py
edc_metadata_rules/tests/tests/test_logic.py
edc_metadata_rules/tests/tests/test_predicates.py
edc_metadata_rules/tests/tests/test_requisition_rule_group.py
edc_metadata_rules/tests/tests/test_site_metadata_rules.py
edc_metadata_rules-0.3.2.dist-info/LICENSE
edc_metadata_rules-0.3.2.dist-info/METADATA
edc_metadata_rules-0.3.2.dist-info/WHEEL
edc_metadata_rules-0.3.2.dist-info/top_level.txt
edc_metadata_rules-0.3.2.dist-info/RECORD
